ashredis/__init__.py
ashredis/enums.py
ashredis/models.py
ashredis/object_redis.py
ashredis/record_base.py
ashredis/utils.py
ashredis-1.2.5.dist-info/METADATA
ashredis-1.2.5.dist-info/WHEEL
ashredis-1.2.5.dist-info/top_level.txt
ashredis-1.2.5.dist-info/RECORD
