Metadata-Version: 2.4
Name: ashredis
Version: 1.2.5
Summary: Async Redis ORM for Python
Author-email: Bloodycat <mrblooddycat@gmail.com>
License-Expression: MIT
Project-URL: Homepage, https://github.com/MrBloodyCat/ashredis
Project-URL: Repository, https://github.com/MrBloodyCat/ashredis
Project-URL: Issues, https://github.com/MrBloodyCat/ashredis/issues
Keywords: redis,orm,async,asyncio,hash
Classifier: Development Status :: 4 - Beta
Classifier: Intended Audience :: Developers
Classifier: Programming Language :: Python :: 3.8
Classifier: Programming Language :: Python :: 3.9
Classifier: Programming Language :: Python :: 3.10
Classifier: Programming Language :: Python :: 3.11
Classifier: Programming Language :: Python :: 3.12
Classifier: Programming Language :: Python :: 3.13
Requires-Python: >=3.8
Requires-Dist: redis>=6.1.0
Provides-Extra: test
Requires-Dist: python-dotenv>=1.1.0; extra == "test"
Provides-Extra: dev
Requires-Dist: black>=21.0; extra == "dev"
Requires-Dist: flake8>=3.9; extra == "dev"
Requires-Dist: isort>=5.0; extra == "dev"
